sanic_statsd/__init__.py
sanic_statsd-0.1.4.dist-info/AUTHORS.rst
sanic_statsd-0.1.4.dist-info/LICENSE
sanic_statsd-0.1.4.dist-info/METADATA
sanic_statsd-0.1.4.dist-info/WHEEL
sanic_statsd-0.1.4.dist-info/top_level.txt
sanic_statsd-0.1.4.dist-info/RECORD
